README
setup.py
soy/__init__.py
soy/bidi.py
soy/data.py
soy/escape.py
soy/tests.py
soy/tofu.py
soy/utils.py
soy.egg-info/PKG-INFO
soy.egg-info/SOURCES.txt
soy.egg-info/dependency_links.txt
soy.egg-info/not-zip-safe
soy.egg-info/top_level.txt