Metadata-Version: 1.1
Name: soy
Version: 2012-12-21-p1
Summary: Client- and server-side templating system for JavaScript, Java and Python.
Home-page: https://bitbucket.org/lalinsky/closure-templates
Author: Lukas Lalinsky
Author-email: lukas@oxygene.sk
License: Apache
Platform: any
Classifier: Development Status :: 3 - Alpha
Classifier: Environment :: Web Environment
Classifier: Intended Audience :: Developers
Classifier: Programming Language :: Python
Classifier: Operating System :: OS Independent
Classifier: Topic :: Internet :: WWW/HTTP :: Dynamic Content
Classifier: Topic :: Software Development :: Libraries :: Python Modules
Classifier: Topic :: Text Processing :: Markup :: HTML
Classifier: License :: OSI Approved :: Apache Software License
